ev_station_assets/__init__.py
ev_station_assets/abstract/assets.py
ev_station_assets/assets.py
ev_station_assets-0.1.0.dist-info/METADATA
ev_station_assets-0.1.0.dist-info/WHEEL
ev_station_assets-0.1.0.dist-info/RECORD
