Metadata-Version: 2.1
Name: ev-station-assets
Version: 0.1.0
Summary: 
Author: shara
Author-email: sharabh2019@gmail.com
Requires-Python: >=3.10,<3.13
Classifier: Programming Language :: Python :: 3
Classifier: Programming Language :: Python :: 3.10
Classifier: Programming Language :: Python :: 3.11
Requires-Dist: pandas (>=2.1.1,<3.0.0)
Requires-Dist: plotly (>=5.17.0,<6.0.0)
Requires-Dist: pydantic (>=2.4.2,<3.0.0)
